{
  "name": "GetRole",
  "description": "Get role with its functionalities by it\u0027s ID.",
  "request": {
    "properties": [
      {
        "name": "FlattenElevationFunctionalities",
        "description": "Merge the normal and elevated functionalities into single records.",
        "type": "bool"
      },
      {
        "name": "ID",
        "description": null,
        "type": "int64"
      }
    ]
  },
  "response": {
    "properties": [
      {
        "name": "Result",
        "description": null,
        "type": "EVA.Core.Management.Rights.RoleWithFunctionalitiesDto"
      }
    ]
  }
}