{
  "name": "GetReturnToSupplierRequestByID",
  "description": "Get a ReturnToSupplierRequest",
  "request": {
    "properties": [
      {
        "name": "ID",
        "description": null,
        "type": "int64"
      }
    ]
  },
  "response": {
    "properties": [
      {
        "name": "CountryID",
        "description": null,
        "type": "string"
      },
      {
        "name": "Filters",
        "description": null,
        "type": "map"
      },
      {
        "name": "LanguageID",
        "description": null,
        "type": "string"
      },
      {
        "name": "Name",
        "description": null,
        "type": "string"
      },
      {
        "name": "OrganizationUnitSetID",
        "description": null,
        "type": "int64"
      },
      {
        "name": "OrganizationUnitSetName",
        "description": null,
        "type": "string"
      },
      {
        "name": "ProductSearchTemplateID",
        "description": null,
        "type": "int64"
      },
      {
        "name": "ProductSearchTemplateName",
        "description": null,
        "type": "string"
      },
      {
        "name": "RecallPercentage",
        "description": null,
        "type": "float128"
      },
      {
        "name": "ReturnReasonID",
        "description": null,
        "type": "int64"
      },
      {
        "name": "ReturnReasonName",
        "description": null,
        "type": "string"
      },
      {
        "name": "Status",
        "description": null,
        "type": "EVA.Core.Orders.ReturnToSupplier.ReturnToSupplierRequestStatus"
      }
    ]
  }
}