{
  "typename": "ProductAmountTieredAmountDiscountActionData",
  "assembly": "EVA.Core",
  "description": null,
  "usage": {
    "request": true,
    "response": true
  },
  "enumIsFlag": null,
  "typeArguments": [],
  "typeDependencies": [
    "EVA.Core.DataModels.FinancialDespersionType",
    "EVA.Core.Discounts.DiscountProductSet",
    "EVA.Core.Discounts.ProductAmountTieredAmountDiscountActionData\u002BTier"
  ],
  "extends": null,
  "properties": {
    "FinancialDispersion": {
      "type": {
        "ref": "EVA.Core.DataModels.FinancialDespersionType",
        "args": [],
        "shared": null,
        "nullable": false
      },
      "description": null,
      "skippable": false,
      "deprecated": null,
      "required": null,
      "requiredAllowEmpty": null,
      "minValue": null,
      "maxValue": null,
      "stringLengthConstraint": null,
      "stringRegexConstraint": null,
      "datamodel": null,
      "allowedValues": []
    },
    "FinancialDispersionScriptID": {
      "type": {
        "ref": "id",
        "args": [],
        "shared": null,
        "nullable": true
      },
      "description": null,
      "skippable": false,
      "deprecated": null,
      "required": null,
      "requiredAllowEmpty": null,
      "minValue": null,
      "maxValue": null,
      "stringLengthConstraint": null,
      "stringRegexConstraint": null,
      "datamodel": null,
      "allowedValues": []
    },
    "IdenticalProductsOnly": {
      "type": {
        "ref": "bool",
        "args": [],
        "shared": null,
        "nullable": false
      },
      "description": null,
      "skippable": false,
      "deprecated": null,
      "required": null,
      "requiredAllowEmpty": null,
      "minValue": null,
      "maxValue": null,
      "stringLengthConstraint": null,
      "stringRegexConstraint": null,
      "datamodel": null,
      "allowedValues": []
    },
    "ProductSet": {
      "type": {
        "ref": "EVA.Core.Discounts.DiscountProductSet",
        "args": [],
        "shared": null,
        "nullable": true
      },
      "description": null,
      "skippable": false,
      "deprecated": null,
      "required": null,
      "requiredAllowEmpty": null,
      "minValue": null,
      "maxValue": null,
      "stringLengthConstraint": null,
      "stringRegexConstraint": null,
      "datamodel": null,
      "allowedValues": []
    },
    "Tiers": {
      "type": {
        "ref": "array",
        "args": [
          {
            "ref": "EVA.Core.Discounts.ProductAmountTieredAmountDiscountActionData\u002BTier",
            "args": [],
            "shared": null,
            "nullable": true
          }
        ],
        "shared": null,
        "nullable": true
      },
      "description": null,
      "skippable": false,
      "deprecated": null,
      "required": null,
      "requiredAllowEmpty": null,
      "minValue": null,
      "maxValue": null,
      "stringLengthConstraint": null,
      "stringRegexConstraint": null,
      "datamodel": null,
      "allowedValues": []
    }
  },
  "enumValues": {},
  "parent": null
}