{
  "typename": "SearchUsers",
  "assembly": "EVA.Core",
  "description": "Execute a search through the users\n\nFiltering is possible on all kinds of properties. By default the search results will be restricted to users in the current country.",
  "usage": {
    "request": true,
    "response": false
  },
  "typeArguments": [],
  "typeDependencies": [
    "EVA.Core.PagedResultRequest\u00601",
    "EVA.Core.Users.SearchUsersResponse",
    "EVA.Core.UserTypes"
  ],
  "extends": {
    "ref": "EVA.Core.PagedResultRequest\u00601",
    "args": [
      {
        "ref": "EVA.Core.Users.SearchUsersResponse",
        "args": [],
        "nullable": true
      }
    ],
    "nullable": false
  },
  "properties": {
    "AssignedEmployeeID": {
      "type": {
        "ref": "int64",
        "args": [],
        "nullable": true
      },
      "skippable": false,
      "datamodel": {
        "name": "User",
        "lenient": false,
        "supportsCustomID": true,
        "isEvaID": true,
        "isExternalID": false
      },
      "allowedValues": []
    },
    "CustomFields": {
      "type": {
        "ref": "map",
        "args": [
          {
            "ref": "int64",
            "args": [],
            "nullable": false
          },
          {
            "ref": "string",
            "args": [],
            "nullable": true
          }
        ],
        "nullable": true
      },
      "skippable": false,
      "allowedValues": []
    },
    "Data": {
      "type": {
        "ref": "map",
        "args": [
          {
            "ref": "string",
            "args": [],
            "nullable": true
          },
          {
            "ref": "string",
            "args": [],
            "nullable": true
          }
        ],
        "nullable": true
      },
      "skippable": false,
      "allowedValues": []
    },
    "DateOfBirth": {
      "type": {
        "ref": "date",
        "args": [],
        "nullable": true
      },
      "skippable": false,
      "allowedValues": []
    },
    "EmailAddress": {
      "type": {
        "ref": "string",
        "args": [],
        "nullable": true
      },
      "skippable": false,
      "allowedValues": []
    },
    "EmployeeNumber": {
      "type": {
        "ref": "string",
        "args": [],
        "nullable": true
      },
      "skippable": false,
      "allowedValues": []
    },
    "FiscalID": {
      "type": {
        "ref": "string",
        "args": [],
        "nullable": true
      },
      "skippable": false,
      "allowedValues": []
    },
    "IncludeAllCountries": {
      "type": {
        "ref": "bool",
        "args": [],
        "nullable": true
      },
      "description": "By default the search will only return users from the same Country as the current OrganizationUnit.\nOptionally an extensive search can be performed by enabling this option. But keep in mind this will take some time in real production scenario\u0027s.\nIt is advised to only show this option in the frontend after an intial search has been done in the current country.",
      "skippable": false,
      "allowedValues": []
    },
    "IncludeCustomers": {
      "type": {
        "ref": "bool",
        "args": [],
        "nullable": false
      },
      "skippable": false,
      "required": {
        "current": true
      },
      "requiredAllowEmpty": {
        "current": false
      },
      "allowedValues": []
    },
    "IncludeEmployees": {
      "type": {
        "ref": "bool",
        "args": [],
        "nullable": false
      },
      "skippable": false,
      "required": {
        "current": true
      },
      "requiredAllowEmpty": {
        "current": false
      },
      "allowedValues": []
    },
    "Name": {
      "type": {
        "ref": "string",
        "args": [],
        "nullable": true
      },
      "skippable": false,
      "allowedValues": []
    },
    "PhoneNumber": {
      "type": {
        "ref": "string",
        "args": [],
        "nullable": true
      },
      "skippable": false,
      "allowedValues": []
    },
    "PricingGroupID": {
      "type": {
        "ref": "string",
        "args": [],
        "nullable": true
      },
      "skippable": false,
      "allowedValues": []
    },
    "PrimaryOrganizationUnitID": {
      "type": {
        "ref": "int64",
        "args": [],
        "nullable": true
      },
      "skippable": false,
      "datamodel": {
        "name": "OrganizationUnit",
        "lenient": false,
        "supportsCustomID": true,
        "isEvaID": true,
        "isExternalID": false
      },
      "allowedValues": []
    },
    "RoleID": {
      "type": {
        "ref": "int64",
        "args": [],
        "nullable": true
      },
      "skippable": false,
      "datamodel": {
        "name": "Role",
        "lenient": false,
        "supportsCustomID": true,
        "isEvaID": true,
        "isExternalID": false
      },
      "allowedValues": []
    },
    "SearchQuery": {
      "type": {
        "ref": "string",
        "args": [],
        "nullable": true
      },
      "skippable": false,
      "allowedValues": []
    },
    "SocialSecurityNumber": {
      "type": {
        "ref": "string",
        "args": [],
        "nullable": true
      },
      "skippable": false,
      "allowedValues": []
    },
    "Types": {
      "type": {
        "ref": "EVA.Core.UserTypes",
        "args": [],
        "nullable": true
      },
      "skippable": false,
      "allowedValues": []
    },
    "UserIDs": {
      "type": {
        "ref": "array",
        "args": [
          {
            "ref": "int64",
            "args": [],
            "nullable": false
          }
        ],
        "nullable": true
      },
      "skippable": false,
      "datamodel": {
        "name": "User",
        "lenient": false,
        "supportsCustomID": true,
        "isEvaID": true,
        "isExternalID": false
      },
      "allowedValues": []
    },
    "VatNumber": {
      "type": {
        "ref": "string",
        "args": [],
        "nullable": true
      },
      "skippable": false,
      "allowedValues": []
    },
    "ZipCode": {
      "type": {
        "ref": "string",
        "args": [],
        "nullable": true
      },
      "skippable": false,
      "allowedValues": []
    }
  }
}