{
  "typename": "Type",
  "assembly": "EVA.BI",
  "usage": {
    "request": false,
    "response": true
  },
  "enumIsFlag": false,
  "typeArguments": [],
  "typeDependencies": [],
  "enumValues": {
    "City": {
      "value": 2,
      "extends": []
    },
    "Country": {
      "value": 4,
      "extends": []
    },
    "None": {
      "value": 0,
      "extends": []
    },
    "Region": {
      "value": 3,
      "extends": []
    },
    "Root": {
      "value": 5,
      "extends": []
    },
    "Shop": {
      "value": 1,
      "extends": []
    }
  },
  "parent": "EVA.BI.Services.GetStoresForUserResponse"
}