{
  "typename": "CreateRefund",
  "assembly": "EVA.Core",
  "description": "Create a refund\n\nWith this service a refund can be done based on an existing PaymentTransaction, or without it for an Order.\n\nIt is required to specify a transaction or to specify the PaymentType to use.\n\nWhen no Amount is specified the open amount of the order will be used.",
  "usage": {
    "request": true,
    "response": false
  },
  "enumIsFlag": null,
  "typeArguments": [],
  "typeDependencies": [
    "EVA.Core.RequestMessage\u00601",
    "EVA.Core.Payments.CreateRefundResponse"
  ],
  "extends": {
    "ref": "EVA.Core.RequestMessage\u00601",
    "args": [
      {
        "ref": "EVA.Core.Payments.CreateRefundResponse",
        "args": [],
        "shared": null,
        "nullable": true
      }
    ],
    "shared": null,
    "nullable": false
  },
  "properties": {
    "Amount": {
      "type": {
        "ref": "float128",
        "args": [],
        "shared": null,
        "nullable": true
      },
      "description": null,
      "skippable": false,
      "deprecated": null,
      "required": null,
      "requiredAllowEmpty": null,
      "minValue": {
        "current": 0,
        "new": null,
        "announced": null,
        "active": null,
        "comment": null
      },
      "maxValue": null,
      "stringLengthConstraint": null,
      "stringRegexConstraint": null,
      "datamodel": null,
      "allowedValues": []
    },
    "CurrencyID": {
      "type": {
        "ref": "string",
        "args": [],
        "shared": null,
        "nullable": true
      },
      "description": null,
      "skippable": false,
      "deprecated": null,
      "required": null,
      "requiredAllowEmpty": null,
      "minValue": null,
      "maxValue": null,
      "stringLengthConstraint": null,
      "stringRegexConstraint": null,
      "datamodel": {
        "name": "Currency",
        "lenient": false,
        "supportsCustomID": false,
        "supportsSystemID": false,
        "isEvaID": true,
        "isExternalID": false
      },
      "allowedValues": []
    },
    "OrderID": {
      "type": {
        "ref": "id",
        "args": [],
        "shared": null,
        "nullable": true
      },
      "description": null,
      "skippable": false,
      "deprecated": null,
      "required": null,
      "requiredAllowEmpty": null,
      "minValue": null,
      "maxValue": null,
      "stringLengthConstraint": null,
      "stringRegexConstraint": null,
      "datamodel": {
        "name": "Order",
        "lenient": false,
        "supportsCustomID": true,
        "supportsSystemID": true,
        "isEvaID": true,
        "isExternalID": false
      },
      "allowedValues": []
    },
    "PaymentTransactionID": {
      "type": {
        "ref": "id",
        "args": [],
        "shared": null,
        "nullable": true
      },
      "description": null,
      "skippable": false,
      "deprecated": null,
      "required": null,
      "requiredAllowEmpty": null,
      "minValue": null,
      "maxValue": null,
      "stringLengthConstraint": null,
      "stringRegexConstraint": null,
      "datamodel": {
        "name": "PaymentTransaction",
        "lenient": false,
        "supportsCustomID": true,
        "supportsSystemID": false,
        "isEvaID": true,
        "isExternalID": false
      },
      "allowedValues": []
    },
    "PaymentTypeID": {
      "type": {
        "ref": "id",
        "args": [],
        "shared": null,
        "nullable": true
      },
      "description": null,
      "skippable": false,
      "deprecated": null,
      "required": null,
      "requiredAllowEmpty": null,
      "minValue": null,
      "maxValue": null,
      "stringLengthConstraint": null,
      "stringRegexConstraint": null,
      "datamodel": {
        "name": "PaymentType",
        "lenient": false,
        "supportsCustomID": false,
        "supportsSystemID": false,
        "isEvaID": true,
        "isExternalID": false
      },
      "allowedValues": []
    },
    "Properties": {
      "type": {
        "ref": "object",
        "args": [],
        "shared": null,
        "nullable": true
      },
      "description": null,
      "skippable": false,
      "deprecated": null,
      "required": null,
      "requiredAllowEmpty": null,
      "minValue": null,
      "maxValue": null,
      "stringLengthConstraint": null,
      "stringRegexConstraint": null,
      "datamodel": null,
      "allowedValues": []
    }
  },
  "enumValues": {},
  "parent": null
}