{
  "typename": "TransputJobsMonitorResultData",
  "assembly": "EVA.Monitor",
  "namespace": "EVA.Monitor.MonitorHandlers.TransputJobs",
  "usage": {
    "request": false,
    "response": true
  },
  "typeArguments": [],
  "typeDependencies": [
    "EVA.Monitor.MonitorHandlers.TransputJobs.TransputJobsMonitorResultData\u002BJobDetails"
  ],
  "properties": {
    "Jobs": {
      "type": {
        "ref": "array",
        "args": [
          {
            "ref": "EVA.Monitor.MonitorHandlers.TransputJobs.TransputJobsMonitorResultData\u002BJobDetails",
            "args": [],
            "nullable": true
          }
        ],
        "nullable": true
      },
      "skippable": false,
      "allowedValues": []
    }
  }
}