{
  "typename": "GetValueAddedLogisticTasks",
  "assembly": "EVA.Core",
  "usage": {
    "request": true,
    "response": false
  },
  "typeArguments": [],
  "typeDependencies": [
    "EVA.Core.RequestMessage\u00601",
    "EVA.Core.Types.ValueAddedLogistics.Services.GetValueAddedLogisticTasksResponse"
  ],
  "extends": {
    "ref": "EVA.Core.RequestMessage\u00601",
    "args": [
      {
        "ref": "EVA.Core.Types.ValueAddedLogistics.Services.GetValueAddedLogisticTasksResponse",
        "args": [],
        "nullable": true
      }
    ],
    "nullable": false
  },
  "properties": {
    "OrderID": {
      "type": {
        "ref": "int64",
        "args": [],
        "nullable": true
      },
      "skippable": false,
      "allowedValues": []
    },
    "OrderLineIDs": {
      "type": {
        "ref": "array",
        "args": [
          {
            "ref": "int64",
            "args": [],
            "nullable": false
          }
        ],
        "nullable": true
      },
      "skippable": false,
      "allowedValues": []
    }
  }
}