{
  "typename": "RepairUserTaskData",
  "assembly": "EVA.Core",
  "description": null,
  "usage": {
    "request": false,
    "response": true
  },
  "enumIsFlag": null,
  "typeArguments": [],
  "typeDependencies": [
    "EVA.Core.Search.IProductSearchItemPrimaryImage"
  ],
  "extends": null,
  "properties": {
    "ProductImage": {
      "type": {
        "ref": "EVA.Core.Search.IProductSearchItemPrimaryImage",
        "args": [],
        "shared": null,
        "nullable": true
      },
      "description": null,
      "skippable": false,
      "deprecated": null,
      "required": null,
      "requiredAllowEmpty": null,
      "minValue": null,
      "maxValue": null,
      "stringLengthConstraint": null,
      "datamodel": null,
      "allowedValues": []
    },
    "ProductName": {
      "type": {
        "ref": "string",
        "args": [],
        "shared": null,
        "nullable": true
      },
      "description": null,
      "skippable": false,
      "deprecated": null,
      "required": null,
      "requiredAllowEmpty": null,
      "minValue": null,
      "maxValue": null,
      "stringLengthConstraint": null,
      "datamodel": null,
      "allowedValues": []
    }
  },
  "enumValues": {},
  "parent": null
}