{
  "typename": "ListCashDepositsItem",
  "assembly": "EVA.Core",
  "namespace": "EVA.Core.Finance.Cash",
  "usage": {
    "request": false,
    "response": true
  },
  "typeArguments": [],
  "typeDependencies": [
    "EVA.Core.DataModels.CashDepositStatus",
    "EVA.Core.DataModels.CashJournalTypes"
  ],
  "properties": {
    "Amount": {
      "type": {
        "ref": "float128",
        "args": [],
        "nullable": false
      },
      "skippable": false,
      "allowedValues": []
    },
    "BankNotes": {
      "type": {
        "ref": "map",
        "args": [
          {
            "ref": "float128",
            "args": [],
            "nullable": false
          },
          {
            "ref": "int32",
            "args": [],
            "nullable": false
          }
        ],
        "nullable": true
      },
      "skippable": false,
      "allowedValues": []
    },
    "Coins": {
      "type": {
        "ref": "map",
        "args": [
          {
            "ref": "float128",
            "args": [],
            "nullable": false
          },
          {
            "ref": "int32",
            "args": [],
            "nullable": false
          }
        ],
        "nullable": true
      },
      "skippable": false,
      "allowedValues": []
    },
    "CreationTime": {
      "type": {
        "ref": "date",
        "args": [],
        "nullable": false
      },
      "skippable": false,
      "allowedValues": []
    },
    "CurrencyID": {
      "type": {
        "ref": "string",
        "args": [],
        "nullable": true
      },
      "skippable": false,
      "datamodel": {
        "name": "Currency",
        "lenient": false,
        "supportsCustomID": false,
        "isEvaID": true,
        "isExternalID": false
      },
      "allowedValues": []
    },
    "DeviceID": {
      "type": {
        "ref": "int64",
        "args": [],
        "nullable": false
      },
      "skippable": false,
      "datamodel": {
        "name": "Device",
        "lenient": false,
        "supportsCustomID": false,
        "isEvaID": true,
        "isExternalID": false
      },
      "allowedValues": []
    },
    "DeviceName": {
      "type": {
        "ref": "string",
        "args": [],
        "nullable": false
      },
      "skippable": false,
      "required": {
        "current": true
      },
      "requiredAllowEmpty": {
        "current": false
      },
      "allowedValues": []
    },
    "ID": {
      "type": {
        "ref": "int64",
        "args": [],
        "nullable": false
      },
      "skippable": false,
      "datamodel": {
        "name": "CashDeposit",
        "lenient": false,
        "supportsCustomID": false,
        "isEvaID": true,
        "isExternalID": false
      },
      "allowedValues": []
    },
    "Number": {
      "type": {
        "ref": "string",
        "args": [],
        "nullable": true
      },
      "skippable": false,
      "allowedValues": []
    },
    "PaymentTypeID": {
      "type": {
        "ref": "int64",
        "args": [],
        "nullable": true
      },
      "skippable": false,
      "datamodel": {
        "name": "PaymentType",
        "lenient": false,
        "supportsCustomID": false,
        "isEvaID": true,
        "isExternalID": false
      },
      "allowedValues": []
    },
    "PaymentTypeName": {
      "type": {
        "ref": "string",
        "args": [],
        "nullable": true
      },
      "skippable": false,
      "allowedValues": []
    },
    "SignatureBlobID": {
      "type": {
        "ref": "guid",
        "args": [],
        "nullable": true
      },
      "skippable": false,
      "allowedValues": []
    },
    "Status": {
      "type": {
        "ref": "EVA.Core.DataModels.CashDepositStatus",
        "args": [],
        "nullable": true
      },
      "skippable": false,
      "allowedValues": []
    },
    "Type": {
      "type": {
        "ref": "EVA.Core.DataModels.CashJournalTypes",
        "args": [],
        "nullable": true
      },
      "skippable": false,
      "allowedValues": []
    }
  }
}