{
  "typename": "ListFullStockCountResultResponse",
  "assembly": "EVA.Core",
  "usage": {
    "request": false,
    "response": true
  },
  "typeArguments": [],
  "typeDependencies": [
    "EVA.Core.PagedResultResponse\u00601",
    "EVA.Core.UserTasks.FullStockCountUserTask.FullStockCountResult"
  ],
  "extends": {
    "ref": "EVA.Core.PagedResultResponse\u00601",
    "args": [
      {
        "ref": "EVA.Core.UserTasks.FullStockCountUserTask.FullStockCountResult",
        "args": [],
        "nullable": true
      }
    ],
    "nullable": false
  },
  "properties": {
    "FullStockCountCompletionTime": {
      "type": {
        "ref": "date",
        "args": [],
        "nullable": true
      },
      "skippable": false,
      "allowedValues": []
    },
    "FullStockCountStartTime": {
      "type": {
        "ref": "date",
        "args": [],
        "nullable": true
      },
      "skippable": false,
      "allowedValues": []
    }
  }
}