{
  "typename": "StockSortingStrategy",
  "assembly": "EVA.PIM.Core",
  "namespace": "EVA.PIM.Core.DataModels",
  "usage": {
    "request": true,
    "response": true
  },
  "typeArguments": [],
  "typeDependencies": [
    "EVA.PIM.Core.DataModels.ProductSearchStrategyModel\u002BStockFilterTypes"
  ],
  "properties": {
    "SortByStock": {
      "type": {
        "ref": "bool",
        "args": [],
        "nullable": false
      },
      "skippable": false,
      "allowedValues": []
    },
    "Type": {
      "type": {
        "ref": "EVA.PIM.Core.DataModels.ProductSearchStrategyModel\u002BStockFilterTypes",
        "args": [],
        "nullable": true
      },
      "skippable": false,
      "allowedValues": []
    }
  },
  "parent": "EVA.PIM.Core.DataModels.ProductSearchStrategyModel"
}