{
  "typename": "PrintReturnToSupplierReceipt",
  "assembly": "EVA.Core",
  "description": "Print the return to supplier order receipt.",
  "usage": {
    "request": true,
    "response": false
  },
  "enumIsFlag": null,
  "typeArguments": [],
  "typeDependencies": [
    "EVA.Core.RequestMessageWithEmptyResponse"
  ],
  "extends": {
    "ref": "EVA.Core.RequestMessageWithEmptyResponse",
    "args": [],
    "shared": null,
    "nullable": false
  },
  "properties": {
    "OrderID": {
      "type": {
        "ref": "int64",
        "args": [],
        "shared": null,
        "nullable": false
      },
      "description": null,
      "skippable": false,
      "deprecated": null,
      "required": {
        "current": true,
        "new": null,
        "announced": null,
        "active": null,
        "comment": null
      },
      "requiredAllowEmpty": {
        "current": false,
        "new": null,
        "announced": null,
        "active": null,
        "comment": null
      },
      "minValue": null,
      "maxValue": null,
      "stringLengthConstraint": null,
      "stringRegexConstraint": null,
      "datamodel": {
        "name": "Order",
        "lenient": false,
        "supportsCustomID": true,
        "isEvaID": true,
        "isExternalID": false
      },
      "allowedValues": []
    },
    "StationID": {
      "type": {
        "ref": "int64",
        "args": [],
        "shared": null,
        "nullable": false
      },
      "description": null,
      "skippable": false,
      "deprecated": null,
      "required": {
        "current": true,
        "new": null,
        "announced": null,
        "active": null,
        "comment": null
      },
      "requiredAllowEmpty": {
        "current": false,
        "new": null,
        "announced": null,
        "active": null,
        "comment": null
      },
      "minValue": null,
      "maxValue": null,
      "stringLengthConstraint": null,
      "stringRegexConstraint": null,
      "datamodel": {
        "name": "Station",
        "lenient": false,
        "supportsCustomID": false,
        "isEvaID": true,
        "isExternalID": false
      },
      "allowedValues": []
    }
  },
  "enumValues": {},
  "parent": null
}