{
  "typename": "StartStockReplenishmentResponse",
  "assembly": "EVA.Core",
  "usage": {
    "request": false,
    "response": true
  },
  "typeArguments": [],
  "typeDependencies": [
    "EVA.Core.ResponseMessage",
    "EVA.Core.UserTasktypes.StockReplenishment.StockReplenishmentWorkSet"
  ],
  "extends": {
    "ref": "EVA.Core.ResponseMessage",
    "args": [],
    "nullable": false
  },
  "properties": {
    "WorkSet": {
      "type": {
        "ref": "EVA.Core.UserTasktypes.StockReplenishment.StockReplenishmentWorkSet",
        "args": [],
        "nullable": true
      },
      "skippable": false,
      "allowedValues": []
    }
  }
}