{
  "typename": "GetOrganizationUnitSetDetailsResponse",
  "assembly": "EVA.Core.Services.Management",
  "namespace": "EVA.Core.Services.Management.OrganizationUnitSets",
  "usage": {
    "request": false,
    "response": true
  },
  "typeArguments": [],
  "typeDependencies": [
    "EVA.API.ResponseMessage",
    "EVA.Core.Services.Management.OrganizationUnitSets.GetOrganizationUnitSetDetailsResponse\u002BOrganizationUnitSubset",
    "EVA.Core.Services.Management.OrganizationUnitSets.OrganizationUnitSetDetails"
  ],
  "extends": {
    "ref": "EVA.API.ResponseMessage",
    "args": [],
    "nullable": false
  },
  "properties": {
    "DeclaredSubsets": {
      "type": {
        "ref": "array",
        "args": [
          {
            "ref": "EVA.Core.Services.Management.OrganizationUnitSets.GetOrganizationUnitSetDetailsResponse\u002BOrganizationUnitSubset",
            "args": [],
            "nullable": true
          }
        ],
        "nullable": true
      },
      "skippable": false,
      "allowedValues": []
    },
    "Set": {
      "type": {
        "ref": "EVA.Core.Services.Management.OrganizationUnitSets.OrganizationUnitSetDetails",
        "args": [],
        "nullable": true
      },
      "skippable": false,
      "allowedValues": []
    }
  }
}