{
  "typename": "GetCurrentFinancialPeriodSummary",
  "assembly": "EVA.Core.Services",
  "namespace": "EVA.Core.Services.Finance",
  "description": "Returns a summary of the current financial period of the organization unit that the user is currently logged on to. The\nresult of this service can be used to retrieve more details of the financial period via the\n\u0060GetFinancialPeriodDetails\u0060 service.",
  "usage": {
    "request": true,
    "response": false
  },
  "typeArguments": [],
  "typeDependencies": [
    "EVA.API.RequestMessage\u00601",
    "EVA.Core.Services.Finance.GetCurrentFinancialPeriodSummaryResponse"
  ],
  "extends": {
    "ref": "EVA.API.RequestMessage\u00601",
    "args": [
      {
        "ref": "EVA.Core.Services.Finance.GetCurrentFinancialPeriodSummaryResponse",
        "args": [],
        "nullable": true
      }
    ],
    "nullable": false
  }
}