{
  "typename": "GetMonitorNotificationEmailRecipientsResponse",
  "assembly": "EVA.Monitor",
  "usage": {
    "request": false,
    "response": true
  },
  "typeArguments": [],
  "typeDependencies": [
    "EVA.Core.ResponseMessage",
    "EVA.Monitor.Services.Notifications.GetMonitorNotificationEmailRecipientsResponse\u002BEmailRecipient"
  ],
  "extends": {
    "ref": "EVA.Core.ResponseMessage",
    "args": [],
    "nullable": false
  },
  "properties": {
    "Recipients": {
      "type": {
        "ref": "array",
        "args": [
          {
            "ref": "EVA.Monitor.Services.Notifications.GetMonitorNotificationEmailRecipientsResponse\u002BEmailRecipient",
            "args": [],
            "nullable": true
          }
        ],
        "nullable": false
      },
      "skippable": false,
      "required": {
        "current": true
      },
      "requiredAllowEmpty": {
        "current": true
      },
      "allowedValues": []
    }
  }
}