{
  "typename": "ListMessageTemplates",
  "assembly": "EVA.Core.Management",
  "description": "List the MessageTemplates",
  "usage": {
    "request": true,
    "response": false
  },
  "typeArguments": [],
  "typeDependencies": [
    "EVA.Core.FilteredPagedResultRequest\u00602",
    "EVA.Core.MessageTemplates.MessageTemplateFilter",
    "EVA.Core.Management.MessageTemplates.ListMessageTemplatesResponse"
  ],
  "extends": {
    "ref": "EVA.Core.FilteredPagedResultRequest\u00602",
    "args": [
      {
        "ref": "EVA.Core.MessageTemplates.MessageTemplateFilter",
        "args": [],
        "nullable": true
      },
      {
        "ref": "EVA.Core.Management.MessageTemplates.ListMessageTemplatesResponse",
        "args": [],
        "nullable": true
      }
    ],
    "nullable": false
  },
  "properties": {}
}