{
  "name": "GetOpeningHoursTemplateByID",
  "assembly": "EVA.Core",
  "path": "/message/GetOpeningHoursTemplateByID",
  "requestType": "EVA.Core.nsOpeningHours.GetOpeningHoursTemplateByID",
  "responseType": "EVA.Core.nsOpeningHours.GetOpeningHoursTemplateResponseByID",
  "deprecated": null,
  "auth": {
    "allowPublic": false,
    "allowLimitedTrust": false,
    "requiredPermissions": [
      {
        "types": 2049,
        "functionality": "OpeningHoursTemplates",
        "scope": 8
      }
    ]
  }
}