{
  "name": "ListOrderLedgerTypes",
  "assembly": "EVA.Core.Services.Management",
  "path": "/api/core/management/ListOrderLedgerTypes",
  "requestType": "EVA.Core.Services.Management.Orders.ListOrderLedgerTypes",
  "responseType": "EVA.Core.Services.Management.Orders.ListOrderLedgerTypesResponse",
  "auth": {
    "allowPublic": false,
    "allowLimitedTrust": false,
    "requiredPermissions": [
      {
        "types": 0,
        "functionality": "OrderLedgerTypes",
        "scope": 8
      }
    ]
  }
}