{
  "name": "ListProductSearchTemplateResults",
  "assembly": "EVA.Core.Management",
  "path": "/message/ListProductSearchTemplateResults",
  "method": "POST",
  "api": null,
  "requestType": "EVA.Core.Management.Products.ListProductSearchTemplateResults",
  "responseType": "EVA.Core.Management.Products.ListProductSearchTemplateResultsResponse",
  "deprecated": {
    "announced": 754,
    "active": 770,
    "comment": "This service has been deprecated and won\u0027t yield any result. To check if a product is part of a product search template, you can use the service \u0027CheckProductSearchTemplateProduct\u0060"
  },
  "auth": {
    "allowPublic": false,
    "allowLimitedTrust": false,
    "requiredPermissions": [
      {
        "types": 2049,
        "functionality": "ProductSearches",
        "scope": 8
      }
    ]
  }
}