{
  "name": "ListOrganizationUnitSuppliers",
  "assembly": "EVA.Core.Services",
  "path": "/api/core/ListOrganizationUnitSuppliers",
  "requestType": "EVA.Core.Services.Suppliers.ListOrganizationUnitSuppliers",
  "responseType": "EVA.Core.Services.Suppliers.ListOrganizationUnitSuppliersResponse",
  "auth": {
    "allowPublic": false,
    "allowLimitedTrust": false,
    "requiredPermissions": [
      {
        "types": 2049,
        "functionality": "OrganizationUnitSuppliers",
        "scope": 8
      }
    ]
  }
}