{
  "name": "UploadAssortmentProducts",
  "assembly": "EVA.Core.Management",
  "path": "/message/UploadAssortmentProducts",
  "method": "POST",
  "api": null,
  "requestType": "EVA.Core.Services.Assortments.UploadAssortmentProducts",
  "responseType": "EVA.Core.Services.Assortments.UploadAssortmentProductsResponse",
  "deprecated": null,
  "auth": {
    "allowPublic": false,
    "requiredPermissions": [
      {
        "types": 2049,
        "functionality": "Assortments",
        "scope": 31
      }
    ]
  }
}